setup.cfg
setup.py
formencode_jsonschema/__init__.py
formencode_jsonschema/converters.py
formencode_jsonschema/schema.py
formencode_jsonschema/typed.py
formencode_jsonschema/utils.py
formencode_jsonschema.egg-info/PKG-INFO
formencode_jsonschema.egg-info/SOURCES.txt
formencode_jsonschema.egg-info/dependency_links.txt
formencode_jsonschema.egg-info/not-zip-safe
formencode_jsonschema.egg-info/requires.txt
formencode_jsonschema.egg-info/top_level.txt
tests/__init__.py
tests/test_dump.py
tests/utils.py