Metadata-Version: 1.1
Name: formencode-jsonschema
Version: 0.1.0
Summary: Dump formencode schema JSON schema using Marshmallow
Home-page: https://github.com/hardtack/formencode_jsonschema
Author: Choi Geonu
Author-email: 6566gun@gmail.com
License: UNKNOWN
Platform: UNKNOWN
Classifier: Intended Audience :: Developers
Classifier: License :: OSI Approved :: MIT License
Classifier: Programming Language :: Python :: 3.4
Classifier: Programming Language :: Python :: 3.5
